indentutils/__init__.py
indentutils-1.2.dist-info/DESCRIPTION.rst
indentutils-1.2.dist-info/METADATA
indentutils-1.2.dist-info/RECORD
indentutils-1.2.dist-info/WHEEL
indentutils-1.2.dist-info/metadata.json
indentutils-1.2.dist-info/top_level.txt
