Metadata-Version: 2.0
Name: indentutils
Version: 1.2
Summary: A package to process indented text
Home-page: UNKNOWN
Author: FranchuFranchu
License: UNKNOWN
Platform: UNKNOWN
Classifier: Programming Language :: Python :: 3
Classifier: License :: OSI Approved :: MIT License
Classifier: Operating System :: OS Independent
